{
  "boards": [
    {
      "name": "PLatform Launch",
      "colums": [
        { "status": "TODO", "num": 4 },
        { "status": "DOING", "num": 4 },
        { "status": "DONE", "num": 3 }
      ],
      "boardId": 1,
      "active": false,
      "sections": [
        {
          "taskID": 1,
          "status": "TODO",
          "name": "build UI for onboarding flow",
          "description": "Bla Bla Bla Bla Bla Bla.......",
          "subtasks": ["build", "Bla Bla Bla"]
        },
        {
          "taskID": 2,
          "status": "TODO",
          "name": "build UI for search",
          "description": "Bla Bla Bla Bla Bla Bla Bla Bla Bla Bla Bla Bla.......",
          "subtasks": ["STart"]
        },
        {
          "taskID": 3,
          "status": "TODO",
          "name": "Build setting UI",
          "description": "Bla Bla Bla Bla Bla Bla.......",
          "subtasks": ["build", "Bla Bla Bla"]
        },
        {
          "taskID": 4,
          "status": "TODO",
          "name": "QA and test all major user journeys",
          "description": "Bla Bla Bla Bla Bla Bla Bla Bla Bla Bla Bla Bla.......",
          "subtasks": ["STart", "STart"]
        },

        {
          "taskID": 5,
          "status": "DOING",
          "name": "Design setting and search pages",
          "description": "Bla Bla Bla Bla Bla Bla.......",
          "subtasks": ["build", "Bla Bla Bla"]
        },
        {
          "taskID": 6,
          "status": "DOING",
          "name": "Add account management endpoints",
          "description": "Bla Bla Bla Bla Bla Bla Bla Bla Bla Bla Bla Bla.......",
          "subtasks": ["STart", "Bla Bla Bla", "STart"]
        },
        {
          "taskID": 7,
          "status": "DOING",
          "name": "Design onboarding flow",
          "description": "Bla Bla Bla Bla Bla Bla.......",
          "subtasks": ["build", "Bla Bla Bla"]
        },
        {
          "taskID": 8,
          "status": "DOING",
          "name": "Add search enpoints",
          "description": "Bla Bla Bla Bla Bla Bla Bla Bla Bla Bla Bla Bla.......",
          "subtasks": ["STart", "Bla Bla Bla"]
        },

        {
          "taskID": 9,
          "status": "DONE",
          "name": "Conduct 5 wireframe tests",
          "description": "Bla Bla Bla Bla Bla Bla.......",
          "subtasks": ["build", "Bla Bla Bla"]
        },
        {
          "taskID": 10,
          "status": "DONE",
          "name": "Market discovery",
          "description": "Bla Bla Bla Bla Bla Bla Bla Bla Bla Bla Bla Bla.......",
          "subtasks": ["STart", "Bla Bla Bla", "STart"]
        },
        {
          "taskID": 11,
          "status": "DONE",
          "name": "Competitor analysis",
          "description": "Bla Bla Bla Bla Bla Bla Bla Bla Bla Bla Bla Bla.......",
          "subtasks": ["STart", "Bla Bla Bla", "STart"]
        }
      ]
    },
    {
      "name": "Roadmap",
      "colums": [
        { "status": "TODO", "num": 2 },
        { "status": "DOING", "num": 1 },
        { "status": "DONE", "num": 3 }
      ],
      "boardId": 1,
      "active": false,
      "sections": [
        {
          "taskID": 1,
          "status": "TODO",
          "name": "Next.JS",
          "description": "Bla Bla Bla Bla Bla Bla.......",
          "subtasks": ["build", "Bla Bla Bla"]
        },
        {
          "taskID": 2,
          "status": "TODO",
          "name": "tailwind css",
          "description": "Bla Bla Bla Bla Bla Bla Bla Bla Bla Bla Bla Bla.......",
          "subtasks": ["STart"]
        },

        {
          "taskID": 3,
          "status": "DOING",
          "name": "React",
          "description": "Bla Bla Bla Bla Bla Bla.......",
          "subtasks": ["build", "Bla Bla Bla"]
        },

        {
          "taskID": 4,
          "status": "DONE",
          "name": "HTML",
          "description": "Bla Bla Bla Bla Bla Bla.......",
          "subtasks": ["build", "Bla Bla Bla"]
        },
        {
          "taskID": 5,
          "status": "DONE",
          "name": "CSS",
          "description": "Bla Bla Bla Bla Bla Bla Bla Bla Bla Bla Bla Bla.......",
          "subtasks": ["STart", "Bla Bla Bla", "STart"]
        },
        {
          "taskID": 6,
          "status": "DONE",
          "name": "JavaScript",
          "description": "Bla Bla Bla Bla Bla Bla.......",
          "subtasks": ["build", "Bla Bla Bla"]
        },
        {
          "taskID": 7,
          "status": "DONE",
          "name": "BootStrap 5",
          "description": "Bla Bla Bla Bla Bla Bla Bla Bla Bla Bla Bla Bla.......",
          "subtasks": ["STart", "Bla Bla Bla", "STart"]
        },
        {
          "taskID": 8,
          "status": "DONE",
          "name": "SASS",
          "description": "Bla Bla Bla Bla Bla Bla.......",
          "subtasks": ["build", "Bla Bla Bla"]
        },
        {
          "taskID": 7,
          "status": "DONE",
          "name": "Typescript",
          "description": "Bla Bla Bla Bla Bla Bla Bla Bla Bla Bla Bla Bla.......",
          "subtasks": ["STart", "Bla Bla Bla", "STart"]
        }
      ]
    }
  ]
}
